setup.py
micropython_redis_modular.egg-info/PKG-INFO
micropython_redis_modular.egg-info/SOURCES.txt
micropython_redis_modular.egg-info/dependency_links.txt
micropython_redis_modular.egg-info/requires.txt
micropython_redis_modular.egg-info/top_level.txt
micropython_redis_modular.egg-info/zip-safe
uredis_modular/__init__.py