Metadata-Version: 1.0
Name: micropython-redis-modular
Version: 0.0.52
Summary: redis module for MicroPython that allows importing only a subset of the redis functionality for low memory environments
Home-page: https://github.com/dhubbard/micropython-redis
Author: Dwight Hubbard
Author-email: dwight@dwighthubbard.com
License: MIT
Platform: UNKNOWN
